{
    "builds": {
        "pdf": {
            "source_dir": "latex/slides",
            "target_dir": "build/pdf",
            "command": "pdflatex",
            "files": [
                "01_grundlagen_1.tex",
                "02_grundlagen_2.tex",
                "03_objektorientierung.tex",
                "04_vererbung_und_polymorphie.tex",
                "05_null_exceptions_schluesselwoerter.tex",
                "06_datenstrukturen.tex"
            ]
        },
        "html": {
            "source_dir": "latex/slides",
            "target_dir": "build/html",
            "command": "hevea",
            "files": []
        }
    }
}
